setup.py
Hoooker/README.md
Hoooker/__init__.py
Hoooker/__test__.py
Hoooker/__tool__.py
Hoooker/interface.py
Hoooker/line.py
Hoooker/message.py
Hoooker.egg-info/PKG-INFO
Hoooker.egg-info/SOURCES.txt
Hoooker.egg-info/dependency_links.txt
Hoooker.egg-info/not-zip-safe
Hoooker.egg-info/top_level.txt