Metadata-Version: 2.1
Name: Hoooker
Version: 0.0.2
Summary: Hoooker
Home-page: UNKNOWN
Author: Theta
License: UNKNOWN
Platform: UNKNOWN
